owlery/__init__.py
owlery/_version.py
owlery/exceptions.py
owlery/py.typed
owlery/signals.py
owlery/utils.py
owlery/services/__init__.py
owlery/services/misc.py
owlery/services/reddit.py
owlery/services/twilio.py
owlery/services/email/__init__.py
owlery/services/email/html.py
owlery/services/email/imap.py
owlery/services/email/pop3.py
owlery/services/email/smtp.py
owlery/services/mms/__init__.py
owlery/services/mms/twilio.py
owlery/services/sms/__init__.py
owlery/services/sms/gsmmodem.py
owlery/services/sms/twilio.py
owlery/services/voice/__init__.py
owlery/services/whatsapp/__init__.py
owlery/services/whatsapp/twilio.py
owlery/services/whatsapp/wabp.py
owlery-0.3.0.dist-info/LICENSE
owlery-0.3.0.dist-info/METADATA
owlery-0.3.0.dist-info/WHEEL
owlery-0.3.0.dist-info/entry_points.txt
owlery-0.3.0.dist-info/top_level.txt
owlery-0.3.0.dist-info/RECORD
